devhub/__init__.py
devhub/__main__.py
devhub/cli.py
devhub/commands/__init__.py
devhub/commands/aikit.py
devhub/commands/theme.py
devhub/utils/__init__.py
devhub/utils/client.py
devhub/utils/templates.py
devhub_cli-0.1.2.dist-info/licenses/LICENSE
devhub_cli-0.1.2.dist-info/METADATA
devhub_cli-0.1.2.dist-info/WHEEL
devhub_cli-0.1.2.dist-info/entry_points.txt
devhub_cli-0.1.2.dist-info/top_level.txt
devhub_cli-0.1.2.dist-info/RECORD
