Metadata-Version: 2.4
Name: devhub-cli
Version: 0.1.2
Summary: CLI interface to devhub
Author: Daniel Rust
License: Apache-2.0
Project-URL: Homepage, https://github.com/devhub/devhub-cli
Project-URL: Changelog, https://github.com/devhub/devhub-cli/releases
Project-URL: Issues, https://github.com/devhub/devhub-cli/issues
Project-URL: CI, https://github.com/devhub/devhub-cli/actions
Requires-Python: >=3.8
License-File: LICENSE
Requires-Dist: click~=8.1.3
Requires-Dist: python-dotenv~=1.0.0
Requires-Dist: djlint~=1.34.0
Requires-Dist: pyyaml~=6.0
Requires-Dist: requests-oauthlib~=2.0.0
Provides-Extra: test
Requires-Dist: pytest; extra == "test"
Dynamic: license-file
